lfc_torque_airtable/__init__.py
lfc_torque_airtable/main.py
lfc_torque_airtable/torque_to_airtable.py
lfc_torque_airtable/utils.py
lfc_torque_airtable/version.py
lfc_torque_airtable-0.1.3.dist-info/licenses/LICENSE.md
lfc_torque_airtable-0.1.3.dist-info/METADATA
lfc_torque_airtable-0.1.3.dist-info/WHEEL
lfc_torque_airtable-0.1.3.dist-info/entry_points.txt
lfc_torque_airtable-0.1.3.dist-info/top_level.txt
lfc_torque_airtable-0.1.3.dist-info/RECORD
