Metadata-Version: 2.4
Name: lfc-torque-airtable
Version: 0.1.3
Summary: Torque airtable connection for LFC
Home-page: https://code.librehq.com/ots/mediawiki/lfc-torque-airtable
Author: Open Tech Strategies, LLC
Author-email: frankduncan@opentechstrategies.com
Classifier: Programming Language :: Python :: 3
Classifier: License :: OSI Approved :: GNU Affero General Public License v3
Classifier: Operating System :: OS Independent
License-File: LICENSE.md
Requires-Dist: torqueclient
Requires-Dist: pyairtable
Dynamic: author
Dynamic: author-email
Dynamic: classifier
Dynamic: description
Dynamic: description-content-type
Dynamic: home-page
Dynamic: license-file
Dynamic: requires-dist
Dynamic: summary
